mangoCR/__init__.py
mangoCR/ocr_extractor.py
mangoCR-0.1.4.dist-info/LICENSE
mangoCR-0.1.4.dist-info/METADATA
mangoCR-0.1.4.dist-info/WHEEL
mangoCR-0.1.4.dist-info/top_level.txt
mangoCR-0.1.4.dist-info/RECORD
