Metadata-Version: 2.1
Name: mangoCR
Version: 0.1.4
Summary: A package to convert PDFs to images and perform OCR.
Home-page: https://github.com/sandeepmj/mangoCR
Author: Sandeep Junnarkar
Author-email: sjnews@gmail.com
License: UNKNOWN
Platform: UNKNOWN
Classifier: Programming Language :: Python :: 3
Classifier: License :: OSI Approved :: MIT License
Classifier: Operating System :: OS Independent
Requires-Python: >=3.6
License-File: LICENSE
Requires-Dist: pymupdf
Requires-Dist: pytesseract
Requires-Dist: Pillow
